odoo/addons/project_hr/README.rst
odoo/addons/project_hr/__init__.py
odoo/addons/project_hr/__manifest__.py
odoo/addons/project_hr/i18n/ca.po
odoo/addons/project_hr/i18n/de.po
odoo/addons/project_hr/i18n/es.po
odoo/addons/project_hr/i18n/hr.po
odoo/addons/project_hr/i18n/it.po
odoo/addons/project_hr/i18n/nl.po
odoo/addons/project_hr/i18n/project_hr.pot
odoo/addons/project_hr/i18n/pt_BR.po
odoo/addons/project_hr/i18n/sl.po
odoo/addons/project_hr/models/__init__.py
odoo/addons/project_hr/models/hr_employee.py
odoo/addons/project_hr/models/project_project.py
odoo/addons/project_hr/models/project_task.py
odoo/addons/project_hr/models/res_users.py
odoo/addons/project_hr/readme/CONFIGURE.md
odoo/addons/project_hr/readme/CONTRIBUTORS.md
odoo/addons/project_hr/readme/DESCRIPTION.md
odoo/addons/project_hr/readme/ROADMAP.md
odoo/addons/project_hr/readme/USAGE.md
odoo/addons/project_hr/static/description/icon.png
odoo/addons/project_hr/static/description/index.html
odoo/addons/project_hr/tests/__init__.py
odoo/addons/project_hr/tests/test_project_hr.py
odoo/addons/project_hr/views/project_project_views.xml
odoo/addons/project_hr/views/project_task_views.xml
odoo_addon_project_hr-18.0.1.0.0.2.dist-info/METADATA
odoo_addon_project_hr-18.0.1.0.0.2.dist-info/WHEEL
odoo_addon_project_hr-18.0.1.0.0.2.dist-info/top_level.txt
odoo_addon_project_hr-18.0.1.0.0.2.dist-info/RECORD
